elementals/__init__.py
elementals/anchor.py
elementals/logger.py
elementals/progress_bar.py
elementals/prompter.py
elementals/status_bar.py
elementals-1.3.3.dist-info/LICENSE
elementals-1.3.3.dist-info/METADATA
elementals-1.3.3.dist-info/WHEEL
elementals-1.3.3.dist-info/top_level.txt
elementals-1.3.3.dist-info/RECORD
