Metadata-Version: 2.1
Name: elementals
Version: 1.3.3
Summary: Basic utilities for CTF (or exploit) scripts
Home-page: https://github.com/eyalitki/elementals
Author: Eyal Itkin
Author-email: eyal.itkin@gmail.com
License: MIT
Classifier: Programming Language :: Python
Classifier: License :: OSI Approved :: MIT License
Classifier: Operating System :: OS Independent
License-File: LICENSE
Requires-Dist: colorama
Requires-Dist: hexdump
Requires-Dist: pydocstyle
Requires-Dist: flake8
Requires-Dist: six
